CHANGELOG.md
LICENSE
MANIFEST.in
README.md
requirements.txt
setup.py
docs/empty
http_lazy_headers/__init__.py
http_lazy_headers/collections_.py
http_lazy_headers/exceptions.py
http_lazy_headers/settings.py
http_lazy_headers/wsgi.py
http_lazy_headers.egg-info/PKG-INFO
http_lazy_headers.egg-info/SOURCES.txt
http_lazy_headers.egg-info/dependency_links.txt
http_lazy_headers.egg-info/not-zip-safe
http_lazy_headers.egg-info/top_level.txt
http_lazy_headers/fields/__init__.py
http_lazy_headers/fields/accept.py
http_lazy_headers/fields/accept_charset.py
http_lazy_headers/fields/accept_encoding.py
http_lazy_headers/fields/accept_language.py
http_lazy_headers/fields/accept_ranges.py
http_lazy_headers/fields/age.py
http_lazy_headers/fields/allow.py
http_lazy_headers/fields/authorization.py
http_lazy_headers/fields/cache_control.py
http_lazy_headers/fields/connection.py
http_lazy_headers/fields/content_disposition.py
http_lazy_headers/fields/content_encoding.py
http_lazy_headers/fields/content_language.py
http_lazy_headers/fields/content_length.py
http_lazy_headers/fields/content_location.py
http_lazy_headers/fields/content_range.py
http_lazy_headers/fields/content_type.py
http_lazy_headers/fields/cookie.py
http_lazy_headers/fields/custom.py
http_lazy_headers/fields/date.py
http_lazy_headers/fields/etag.py
http_lazy_headers/fields/expect.py
http_lazy_headers/fields/expires.py
http_lazy_headers/fields/from_.py
http_lazy_headers/fields/host.py
http_lazy_headers/fields/if_match.py
http_lazy_headers/fields/if_modified_since.py
http_lazy_headers/fields/if_none_match.py
http_lazy_headers/fields/if_range.py
http_lazy_headers/fields/if_unmodified_since.py
http_lazy_headers/fields/last_modified.py
http_lazy_headers/fields/location.py
http_lazy_headers/fields/max_forwards.py
http_lazy_headers/fields/pragma.py
http_lazy_headers/fields/range.py
http_lazy_headers/fields/referer.py
http_lazy_headers/fields/retry_after.py
http_lazy_headers/fields/server.py
http_lazy_headers/fields/set_cookie.py
http_lazy_headers/fields/te.py
http_lazy_headers/fields/trailer.py
http_lazy_headers/fields/transfer_encoding.py
http_lazy_headers/fields/upgrade.py
http_lazy_headers/fields/user_agent.py
