Metadata-Version: 1.1
Name: http-lazy-headers
Version: 0.1.dev0
Summary: Parse, validate and format HTTP headers lazily
Home-page: https://github.com/nitely/http-lazy-headers
Author: Esteban Castro Borsani
Author-email: ecastroborsani@gmail.com
License: MIT License
Platform: UNKNOWN
Classifier: Environment :: Web Environment
Classifier: Intended Audience :: Developers
Classifier: License :: OSI Approved :: MIT License
Classifier: Operating System :: OS Independent
Classifier: Programming Language :: Python
Classifier: Programming Language :: Python :: 3
Classifier: Topic :: Internet :: WWW/HTTP
Classifier: Topic :: Internet :: WWW/HTTP :: Dynamic Content
